{
  "trainingPhrases": [ {
    "parts": [ {
      "text": "how i will reach you",
      "auto": true
    } ],
    "repeatCount": 1,
    "languageCode": "en"
  }, {
    "parts": [ {
      "text": "how i can connect you",
      "auto": true
    } ],
    "repeatCount": 1,
    "languageCode": "en"
  }, {
    "parts": [ {
      "text": "contact us",
      "auto": true
    } ],
    "repeatCount": 1,
    "languageCode": "en"
  }, {
    "parts": [ {
      "text": "address",
      "auto": true
    } ],
    "repeatCount": 1,
    "languageCode": "en"
  }, {
    "parts": [ {
      "text": "email id",
      "auto": true
    } ],
    "repeatCount": 1,
    "languageCode": "en"
  }, {
    "parts": [ {
      "text": "i want to know email id",
      "auto": true
    } ],
    "repeatCount": 1,
    "languageCode": "en"
  }, {
    "parts": [ {
      "text": "I want to know the Address and Email id",
      "auto": true
    } ],
    "repeatCount": 1,
    "languageCode": "en"
  } ]
}
